cargohub/__init__.py
cargohub/functions.py
cargohub-0.0.1.dist-info/METADATA
cargohub-0.0.1.dist-info/WHEEL
cargohub-0.0.1.dist-info/top_level.txt
cargohub-0.0.1.dist-info/RECORD
