Metadata-Version: 2.1
Name: cargohub
Version: 0.0.1
Summary: cargohub official python library
Home-page: https://www.cargohub.app
Author: Sacha Ichbiah
Author-email: sacha.ichbiah@gmail.com
Project-URL: Team website, https://www.cargohub.app
Classifier: Programming Language :: Python :: 3
Classifier: License :: OSI Approved :: MIT License
Classifier: Operating System :: POSIX :: Linux
Classifier: Operating System :: MacOS
Classifier: License :: OSI Approved :: MIT License
Classifier: Intended Audience :: Science/Research
Requires-Python: >=3.6
Requires-Dist: numpy >=1.21.6
Requires-Dist: matplotlib >=3.3.1
